lazycommitpy/__init__.py
lazycommitpy/cli.py
lazycommitpy/commands/__init__.py
lazycommitpy/commands/config.py
lazycommitpy/commands/hooks.py
lazycommitpy/commands/lazycommit.py
lazycommitpy/commands/prepare_commit_msg_hook.py
lazycommitpy/utils/__init__.py
lazycommitpy/utils/config.py
lazycommitpy/utils/error.py
lazycommitpy/utils/fs.py
lazycommitpy/utils/git.py
lazycommitpy/utils/groq.py
lazycommitpy/utils/prompt.py
lazycommitpy-0.1.2.dist-info/METADATA
lazycommitpy-0.1.2.dist-info/WHEEL
lazycommitpy-0.1.2.dist-info/entry_points.txt
lazycommitpy-0.1.2.dist-info/licenses/LICENSE
lazycommitpy-0.1.2.dist-info/RECORD
