Metadata-Version: 2.4
Name: lazycommitpy
Version: 0.1.2
Summary: AI-powered Git commit message generator using Groq
Author: Kartik Labhshetwar
License: Apache-2.0
License-File: LICENSE
Requires-Python: >=3.9
Requires-Dist: groq>=0.9
Requires-Dist: rich>=13
Requires-Dist: typer>=0.12
Provides-Extra: dev
Requires-Dist: build>=1.2; extra == 'dev'
Requires-Dist: mypy>=1.10; extra == 'dev'
Requires-Dist: pytest-cov>=5; extra == 'dev'
Requires-Dist: pytest>=8; extra == 'dev'
Requires-Dist: ruff>=0.5; extra == 'dev'
Requires-Dist: twine>=5; extra == 'dev'
